PowerfulDiceRoller/__init__.py
PowerfulDiceRoller/models/Dice.py
PowerfulDiceRoller/models/DiceThrown.py
PowerfulDiceRoller/models/LarkThrown.py
PowerfulDiceRoller/models/__init__.py
PowerfulDiceRoller/models/errors/DiceError.py
PowerfulDiceRoller/models/errors/NegativeDiceFaces.py
PowerfulDiceRoller/models/errors/NotFoundMethod.py
PowerfulDiceRoller/models/errors/ParseError.py
PowerfulDiceRoller/models/errors/__init__.py
PowerfulDiceRoller/parser/__init__.py
PowerfulDiceRoller/parser/get_result.py
PowerfulDiceRoller/parser/lark_laboers.py
PowerfulDiceRoller/resources/__init__.py
PowerfulDiceRoller/resources/grammar.py
PowerfulDiceRoller-2.1.dist-info/LICENSE
PowerfulDiceRoller-2.1.dist-info/METADATA
PowerfulDiceRoller-2.1.dist-info/WHEEL
PowerfulDiceRoller-2.1.dist-info/top_level.txt
PowerfulDiceRoller-2.1.dist-info/RECORD
